palsql
