Metadata-Version: 1.2
Name: palsql
Version: 1.1
Summary: Sqlite3 Wrapper Class
Home-page: https://github.com/ipal0/palsql
Author: Pal
Author-email: ipal0can@gmail.com
License: GPL
Platform: UNKNOWN
Requires-Python: >=3
